surround_text_jumble_4VxP/__init__.py
surround_text_jumble_4VxP/example.py
surround_text_jumble_4VxP-0.0.1.dist-info/LICENSE
surround_text_jumble_4VxP-0.0.1.dist-info/METADATA
surround_text_jumble_4VxP-0.0.1.dist-info/WHEEL
surround_text_jumble_4VxP-0.0.1.dist-info/top_level.txt
surround_text_jumble_4VxP-0.0.1.dist-info/RECORD
